localstack_granian/__init__.py
localstack_granian/granian.py
localstack_granian/noop.py
localstack_granian-0.0.1.dist-info/METADATA
localstack_granian-0.0.1.dist-info/WHEEL
localstack_granian-0.0.1.dist-info/entry_points.txt
localstack_granian-0.0.1.dist-info/top_level.txt
localstack_granian-0.0.1.dist-info/RECORD
